DaimaZhengjiZhidao/README.md
DaimaZhengjiZhidao/__init__.py
DaimaZhengjiZhidao/__main__.py
DaimaZhengjiZhidao/file.epub
DaimaZhengjiZhidao/index.html
DaimaZhengjiZhidao/css/__init__.py
DaimaZhengjiZhidao/css/annotations.css
DaimaZhengjiZhidao/css/main.css
DaimaZhengjiZhidao/css/normalize.css
DaimaZhengjiZhidao/css/popup.css
DaimaZhengjiZhidao/font/__init__.py
DaimaZhengjiZhidao/font/fontello.eot
DaimaZhengjiZhidao/font/fontello.svg
DaimaZhengjiZhidao/font/fontello.ttf
DaimaZhengjiZhidao/font/fontello.woff
DaimaZhengjiZhidao/img/__init__.py
DaimaZhengjiZhidao/img/annotator-glyph-sprite.png
DaimaZhengjiZhidao/img/annotator-icon-sprite.png
DaimaZhengjiZhidao/img/apple-touch-icon.png
DaimaZhengjiZhidao/img/cancelfullscreen.png
DaimaZhengjiZhidao/img/close.png
DaimaZhengjiZhidao/img/fullscreen.png
DaimaZhengjiZhidao/img/loader.gif
DaimaZhengjiZhidao/img/menu-icon.png
DaimaZhengjiZhidao/img/save.png
DaimaZhengjiZhidao/img/saved.png
DaimaZhengjiZhidao/img/settings-s.png
DaimaZhengjiZhidao/img/settings.png
DaimaZhengjiZhidao/img/star.png
DaimaZhengjiZhidao/js/__init__.py
DaimaZhengjiZhidao/js/epub.js
DaimaZhengjiZhidao/js/epub.min.js
DaimaZhengjiZhidao/js/epub.min.map
DaimaZhengjiZhidao/js/hooks.min.js
DaimaZhengjiZhidao/js/hooks.min.map
DaimaZhengjiZhidao/js/reader.js
DaimaZhengjiZhidao/js/reader.js.map
DaimaZhengjiZhidao/js/reader.min.js
DaimaZhengjiZhidao/js/reader.min.map
DaimaZhengjiZhidao/js/hooks/__init__.py
DaimaZhengjiZhidao/js/hooks/extensions/__init__.py
DaimaZhengjiZhidao/js/hooks/extensions/highlight.js
DaimaZhengjiZhidao/js/libs/__init__.py
DaimaZhengjiZhidao/js/libs/jquery.min.js
DaimaZhengjiZhidao/js/libs/localforage.min.js
DaimaZhengjiZhidao/js/libs/screenfull.js
DaimaZhengjiZhidao/js/libs/screenfull.min.js
DaimaZhengjiZhidao/js/libs/zip.min.js
DaimaZhengjiZhidao/js/plugins/__init__.py
DaimaZhengjiZhidao/js/plugins/hypothesis.js
DaimaZhengjiZhidao/js/plugins/search.js
daima_zhengji_zhidao-2024.3.5.0.dist-info/METADATA
daima_zhengji_zhidao-2024.3.5.0.dist-info/WHEEL
daima_zhengji_zhidao-2024.3.5.0.dist-info/entry_points.txt
daima_zhengji_zhidao-2024.3.5.0.dist-info/top_level.txt
daima_zhengji_zhidao-2024.3.5.0.dist-info/RECORD
